python_project_skeleton/__init__.py
python_project_skeleton/main.ini
python_project_skeleton/main.py
python_project_skeleton/tests/__init__.py
python_project_skeleton/tools/__init__.py
python_project_skeleton/tools/config.py
python_project_skeleton-1.7.data/data/main.ini
python_project_skeleton-1.7.dist-info/LICENSE
python_project_skeleton-1.7.dist-info/METADATA
python_project_skeleton-1.7.dist-info/WHEEL
python_project_skeleton-1.7.dist-info/top_level.txt
python_project_skeleton-1.7.dist-info/RECORD
