Metadata-Version: 2.1
Name: python-project-skeleton
Version: 1.7
Summary: python project skeleton
Home-page: http://github.com/pasuder/python-project-skeleton
Author: Paweł Suder
Author-email: pawel@suder.info
License: UNKNOWN
Download-URL: http://github.com/pasuder/python-project-skeleton
Keywords: skeleton
Platform: UNKNOWN
Classifier: Programming Language :: Python
Classifier: Development Status :: 4 - Beta
Classifier: Environment :: Other Environment
Classifier: Intended Audience :: Developers
Classifier: License :: OSI Approved :: MIT License
Classifier: Operating System :: OS Independent
